rich_utils/__init__.py
rich_utils/progress.py
rich_utils-0.4.0.dist-info/WHEEL
rich_utils-0.4.0.dist-info/METADATA
rich_utils-0.4.0.dist-info/RECORD
