Metadata-Version: 2.1
Name: rich-utils
Version: 0.4.0
Summary: Utility methods and classes for the "rich" package.
License: MIT
Author: Tim Wedde
Author-email: timwedde@icloud.com
Requires-Python: >=3.6,<4.0
Classifier: License :: OSI Approved :: MIT License
Classifier: Programming Language :: Python :: 3
Classifier: Programming Language :: Python :: 3.6
Classifier: Programming Language :: Python :: 3.7
Classifier: Programming Language :: Python :: 3.8
Classifier: Programming Language :: Python :: 3.9
Requires-Dist: rich (>=9.1.0,<10.0.0)
